[
  {
    "q": "1. 国际收支的概念",
    "a": "<b>一国居民在一定时期内与其他国居民之间的各种经济交易收入与支出的总和。</i>"
  },
  {
    "q": "2. 开放经济下的国民收入恒等式",
    "a": "<b>Y = C + I + G + X - M （考虑商品流动）<br>Y = C + I + G + X - M + NFP （考虑生产要素国际流动）</i>"
  },
  {
    "q": "3. NFP",
    "a": "<b>从外国取得的净要素收入，包括付给工人的净报酬、净投资收入（含直接投资与间接投资），以及一国向另一国无偿捐献的现金或其他实际资源。</i>"
  },
  {
    "q": "4. 自主性交易与补偿性交易",
    "a": "<b>自主性交易：完全由于经济目的而从事的交易，具有自发性和分散性。<br>补偿性（调节性）交易：为弥补或调节自主性交易出现的差额而发生的交易，如借款、动用官方储备等，具有集中性和被动性。</i>"
  },
  {
    "q": "5. 国际收支均衡的界定",
    "a": "<b>国内经济处于均衡状态（充分就业、物价稳定）下的自主性国际收支平衡，是一国达到福利最大化的综合政策目标，意味着内外均衡均达到理想状态。</i>"
  },
  {
    "q": "6. 国际收支平衡的识别指标及内容",
    "a": "<b>主要替代指标包括：<ul><li>贸易收支差额（进出口差额）</li><li>经常账户收支差额（综合反映实质资源流动）</li><li>资本与金融账户收支差额（反映资本市场开放程度）</li><li>综合收支差额（总差额）= CA + (KA - R)，反映对储备的压力</li></ul></i>"
  },
  {
    "q": "7. 国际收支失衡的原因",
    "a": "<b><ul><li>偶发性因素（如自然灾害、政局动荡）</li><li>周期性因素（经济周期波动）</li><li>结构性因素（国际分工结构变化与经济结构不适应）</li><li>货币性因素（价格、汇率、利率变化）</li><li>收入性因素（国民收入长期变化）</li></ul></i>"
  },
  {
    "q": "8. 国际收支平衡表的记账（计算）",
    "a": "<b>采用复式记账法，一笔贸易流量对应一笔金融流量。<br>借方表示资产（资源）持有量增加或负债减少；贷方表示资产（资源）持有量减少或负债增加。<br>例如：出口商品记“贷：商品出口”，对应“借：在外国银行存款”。</i>"
  }
]
